otio_kdenlive_adapter/__init__.py
otio_kdenlive_adapter/plugin_manifest.json
otio_kdenlive_adapter/adapters/__init__.py
otio_kdenlive_adapter/adapters/kdenlive.py
otio_kdenlive_adapter-0.0.2.dist-info/LICENSE
otio_kdenlive_adapter-0.0.2.dist-info/METADATA
otio_kdenlive_adapter-0.0.2.dist-info/WHEEL
otio_kdenlive_adapter-0.0.2.dist-info/entry_points.txt
otio_kdenlive_adapter-0.0.2.dist-info/top_level.txt
otio_kdenlive_adapter-0.0.2.dist-info/RECORD
